DaShujuShiyanShouce/README.md
DaShujuShiyanShouce/__init__.py
DaShujuShiyanShouce/__main__.py
DaShujuShiyanShouce/file.epub
DaShujuShiyanShouce/index.html
DaShujuShiyanShouce/css/__init__.py
DaShujuShiyanShouce/css/annotations.css
DaShujuShiyanShouce/css/main.css
DaShujuShiyanShouce/css/normalize.css
DaShujuShiyanShouce/css/popup.css
DaShujuShiyanShouce/font/__init__.py
DaShujuShiyanShouce/font/fontello.eot
DaShujuShiyanShouce/font/fontello.svg
DaShujuShiyanShouce/font/fontello.ttf
DaShujuShiyanShouce/font/fontello.woff
DaShujuShiyanShouce/img/__init__.py
DaShujuShiyanShouce/img/annotator-glyph-sprite.png
DaShujuShiyanShouce/img/annotator-icon-sprite.png
DaShujuShiyanShouce/img/apple-touch-icon.png
DaShujuShiyanShouce/img/cancelfullscreen.png
DaShujuShiyanShouce/img/close.png
DaShujuShiyanShouce/img/fullscreen.png
DaShujuShiyanShouce/img/loader.gif
DaShujuShiyanShouce/img/menu-icon.png
DaShujuShiyanShouce/img/save.png
DaShujuShiyanShouce/img/saved.png
DaShujuShiyanShouce/img/settings-s.png
DaShujuShiyanShouce/img/settings.png
DaShujuShiyanShouce/img/star.png
DaShujuShiyanShouce/js/__init__.py
DaShujuShiyanShouce/js/epub.js
DaShujuShiyanShouce/js/epub.min.js
DaShujuShiyanShouce/js/epub.min.map
DaShujuShiyanShouce/js/hooks.min.js
DaShujuShiyanShouce/js/hooks.min.map
DaShujuShiyanShouce/js/reader.js
DaShujuShiyanShouce/js/reader.js.map
DaShujuShiyanShouce/js/reader.min.js
DaShujuShiyanShouce/js/reader.min.map
DaShujuShiyanShouce/js/hooks/__init__.py
DaShujuShiyanShouce/js/hooks/extensions/__init__.py
DaShujuShiyanShouce/js/hooks/extensions/highlight.js
DaShujuShiyanShouce/js/libs/__init__.py
DaShujuShiyanShouce/js/libs/jquery.min.js
DaShujuShiyanShouce/js/libs/localforage.min.js
DaShujuShiyanShouce/js/libs/screenfull.js
DaShujuShiyanShouce/js/libs/screenfull.min.js
DaShujuShiyanShouce/js/libs/zip.min.js
DaShujuShiyanShouce/js/plugins/__init__.py
DaShujuShiyanShouce/js/plugins/hypothesis.js
DaShujuShiyanShouce/js/plugins/search.js
da_shuju_shiyan_shouce-2024.3.3.0.dist-info/METADATA
da_shuju_shiyan_shouce-2024.3.3.0.dist-info/WHEEL
da_shuju_shiyan_shouce-2024.3.3.0.dist-info/entry_points.txt
da_shuju_shiyan_shouce-2024.3.3.0.dist-info/top_level.txt
da_shuju_shiyan_shouce-2024.3.3.0.dist-info/RECORD
